retronix/__init__.py
retronix.py_benfosterdev-1.1.3.dist-info/LICENSE
retronix.py_benfosterdev-1.1.3.dist-info/METADATA
retronix.py_benfosterdev-1.1.3.dist-info/WHEEL
retronix.py_benfosterdev-1.1.3.dist-info/top_level.txt
retronix.py_benfosterdev-1.1.3.dist-info/RECORD
