Metadata-Version: 2.1
Name: retronix.py-benfosterdev
Version: 1.1.3
Summary: A Python library for the interaction with the Retronix public API
Home-page: https://github.com/retronixmc/retronix.py
Author: Ben Foster
Author-email: ben@benfoster.dev
License: UNKNOWN
Platform: UNKNOWN
Classifier: Programming Language :: Python :: 3
Classifier: License :: OSI Approved :: MIT License
Classifier: Operating System :: OS Independent
Requires-Python: >=3.7
